odoo/addons/stock_move_priority_picking_assign/README.rst
odoo/addons/stock_move_priority_picking_assign/__init__.py
odoo/addons/stock_move_priority_picking_assign/__manifest__.py
odoo/addons/stock_move_priority_picking_assign/i18n/it.po
odoo/addons/stock_move_priority_picking_assign/i18n/stock_move_priority_picking_assign.pot
odoo/addons/stock_move_priority_picking_assign/models/__init__.py
odoo/addons/stock_move_priority_picking_assign/models/stock_move.py
odoo/addons/stock_move_priority_picking_assign/models/stock_picking_type.py
odoo/addons/stock_move_priority_picking_assign/readme/CONFIGURE.md
odoo/addons/stock_move_priority_picking_assign/readme/CONTEXT.md
odoo/addons/stock_move_priority_picking_assign/readme/CONTRIBUTORS.md
odoo/addons/stock_move_priority_picking_assign/readme/DESCRIPTION.md
odoo/addons/stock_move_priority_picking_assign/readme/INSTALL.md
odoo/addons/stock_move_priority_picking_assign/static/description/icon.png
odoo/addons/stock_move_priority_picking_assign/static/description/index.html
odoo/addons/stock_move_priority_picking_assign/tests/__init__.py
odoo/addons/stock_move_priority_picking_assign/tests/test_move_priority.py
odoo/addons/stock_move_priority_picking_assign/views/stock_picking_type.xml
odoo_addon_stock_move_priority_picking_assign-16.0.1.0.0.6.dist-info/METADATA
odoo_addon_stock_move_priority_picking_assign-16.0.1.0.0.6.dist-info/WHEEL
odoo_addon_stock_move_priority_picking_assign-16.0.1.0.0.6.dist-info/top_level.txt
odoo_addon_stock_move_priority_picking_assign-16.0.1.0.0.6.dist-info/RECORD
