Metadata-Version: 2.1
Name: odoo-addon-stock_move_priority_picking_assign
Version: 16.0.1.0.0.6
Summary: This module allows to create a stock movement with a priority and transfer it to the picking during assignation (for new ones)
Home-page: https://github.com/OCA/stock-logistics-workflow
Author: ACSONE SA/NV,Odoo Community Association (OCA)
Author-email: support@odoo-community.org
License: AGPL-3
Classifier: Programming Language :: Python
Classifier: Framework :: Odoo
Classifier: Framework :: Odoo :: 16.0
Classifier: License :: OSI Approved :: GNU Affero General Public License v3
Requires-Python: >=3.10
Requires-Dist: odoo-addon-stock-move-manage-priority <16.1dev,>=16.0dev
Requires-Dist: odoo <16.1dev,>=16.0a
